brewmaster/__init__.py
brewmaster/adapter.py
brewmaster/apis/__init__.py
brewmaster/apis/base.py
brewmaster/apis/caredb.py
brewmaster/apis/courier.py
brewmaster/apis/overlord.py
brewmaster/apis/showboat.py
brewmaster/apis/themes.py
brewmaster/apis/utils.py
brewmaster/barrel.py
brewmaster/basetest.py
brewmaster/cli/__init__.py
brewmaster/cli/docs.py
brewmaster/cli/main.py
brewmaster/exceptions.py
brewmaster/manage.py
brewmaster/objects/__init__.py
brewmaster/objects/base.py
brewmaster/objects/caredb.py
brewmaster/objects/courier.py
brewmaster/objects/cronkite.py
brewmaster/objects/identity.py
brewmaster/objects/lachesis.py
brewmaster/objects/overlord.py
brewmaster/objects/pylon.py
brewmaster/objects/showboat.py
brewmaster/settings/__init__.py
brewmaster/settings/common.py
brewmaster/settings/test.py
brewmaster/templates/module.md
carium_brewmaster-1.21.1.dist-info/LICENSE
carium_brewmaster-1.21.1.dist-info/METADATA
carium_brewmaster-1.21.1.dist-info/WHEEL
carium_brewmaster-1.21.1.dist-info/entry_points.txt
carium_brewmaster-1.21.1.dist-info/RECORD
