Metadata-Version: 2.1
Name: carium-brewmaster
Version: 1.21.1
Summary: Library/utility collection for custom job
License: MIT
Author: Carium Devops
Author-email: devops@carium.com
Requires-Python: >=3.10,<4.0
Classifier: License :: OSI Approved :: MIT License
Classifier: Programming Language :: Python :: 3
Classifier: Programming Language :: Python :: 3.10
Classifier: Programming Language :: Python :: 3.11
Classifier: Programming Language :: Python :: 3.12
Requires-Dist: Django
Requires-Dist: Jinja2
Requires-Dist: cariutils (>=1.15.0,<2.0.0)
Requires-Dist: docstring-parser
Requires-Dist: jq
Requires-Dist: python-dateutil
Requires-Dist: requests
Requires-Dist: responses
